relaxation.cpython-312-x86_64-linux-gnu.so
fretraj/__init__.py
fretraj/burst.py
fretraj/cloud.py
fretraj/console.py
fretraj/export.py
fretraj/fret.py
fretraj/fretraj_gui.py
fretraj/grid.py
fretraj/isosurf.py
fretraj/jupyter.py
fretraj/periodic_table.json
fretraj/relaxation.cpp
fretraj/restraints.py
fretraj/UI/fretraj.ui
fretraj/UI/icon.png
fretraj/UI/restraints.ui
fretraj/UI/settings.ui
fretraj/UI/textpad.ui
fretraj/examples/2m23.pdb
fretraj/examples/2m23_labels.json
fretraj/examples/DNA_hairpin.pdb
fretraj/examples/DNA_hairpin.xtc
fretraj/examples/DNA_hairpin_labels.json
fretraj/examples/doublestranded_DNA.pdb
fretraj/examples/doublestranded_DNA.xtc
fretraj/examples/doublestranded_DNA_labels.json
fretraj/skripts/pymol_vis.sh
fretraj/skripts/vmd_vis.sh
fretraj-0.2.11.dist-info/LICENSE
fretraj-0.2.11.dist-info/METADATA
fretraj-0.2.11.dist-info/WHEEL
fretraj-0.2.11.dist-info/entry_points.txt
fretraj-0.2.11.dist-info/top_level.txt
fretraj-0.2.11.dist-info/RECORD
