Metadata-Version: 2.2
Name: fretraj
Version: 0.2.11
Summary: Predicting FRET with accessible-contact volumes
Author-email: Fabio Steffen <fabio.steffen@chem.uzh.ch>, "Roland K.O. Sigel" <roland.sigel@chem.uzh.ch>, Richard Börner <richard.boerner@hs-mittweida.de>
License: GPL-3.0-or-later
Project-URL: Repository, https://github.com/RNA-FRETools/fretraj
Project-URL: Documentation, https://rna-fretools.github.io/fretraj/
Project-URL: Issues, https://rna-fretools.github.io/fretraj/issues
Keywords: FRET,single-molecule,molecular dynamics,PDB,structure prediction
Classifier: Programming Language :: Python
Classifier: License :: OSI Approved :: GNU General Public License v3 or later (GPLv3+)
Classifier: Operating System :: OS Independent
Classifier: Framework :: Jupyter
Classifier: Topic :: Scientific/Engineering :: Bio-Informatics
Requires-Python: >=3.8
License-File: LICENSE
Requires-Dist: numpy
Requires-Dist: numba
Requires-Dist: pandas
Requires-Dist: mdtraj
Requires-Dist: tqdm
Requires-Dist: jsonschema
Requires-Dist: importlib-metadata
Provides-Extra: dev
Requires-Dist: bumpver; extra == "dev"
Requires-Dist: pytest; extra == "dev"
Requires-Dist: build; extra == "dev"
Requires-Dist: pytest-cov; extra == "dev"
Requires-Dist: pytest-mock; extra == "dev"
Provides-Extra: docs
Requires-Dist: jupyter-book; extra == "docs"
Requires-Dist: ipywidgets; extra == "docs"
Requires-Dist: matplotlib; extra == "docs"
Requires-Dist: seaborn; extra == "docs"
